bpm_ai_core/__init__.py
bpm_ai_core/image_classification/__init__.py
bpm_ai_core/image_classification/image_classifier.py
bpm_ai_core/llm/__init__.py
bpm_ai_core/llm/anthropic_chat/__init__.py
bpm_ai_core/llm/anthropic_chat/_constants.py
bpm_ai_core/llm/anthropic_chat/anthropic_chat.py
bpm_ai_core/llm/anthropic_chat/output_schema.prompt
bpm_ai_core/llm/anthropic_chat/util.py
bpm_ai_core/llm/common/__init__.py
bpm_ai_core/llm/common/blob.py
bpm_ai_core/llm/common/llm.py
bpm_ai_core/llm/common/message.py
bpm_ai_core/llm/common/tool.py
bpm_ai_core/llm/openai_chat/__init__.py
bpm_ai_core/llm/openai_chat/_constants.py
bpm_ai_core/llm/openai_chat/openai_chat.py
bpm_ai_core/llm/openai_chat/util.py
bpm_ai_core/ocr/__init__.py
bpm_ai_core/ocr/amazon_textract.py
bpm_ai_core/ocr/azure_doc_intelligence.py
bpm_ai_core/ocr/ocr.py
bpm_ai_core/pos/__init__.py
bpm_ai_core/pos/pos_tagger.py
bpm_ai_core/prompt/__init__.py
bpm_ai_core/prompt/filters.py
bpm_ai_core/prompt/prompt.py
bpm_ai_core/question_answering/__init__.py
bpm_ai_core/question_answering/amazon_textract_docvqa.py
bpm_ai_core/question_answering/azure_doc_intelligence_docvqa.py
bpm_ai_core/question_answering/question_answering.py
bpm_ai_core/retrieval/__init__.py
bpm_ai_core/retrieval/retrieval.py
bpm_ai_core/speech_recognition/__init__.py
bpm_ai_core/speech_recognition/asr.py
bpm_ai_core/speech_recognition/openai_whisper.py
bpm_ai_core/testing/__init__.py
bpm_ai_core/testing/fake_llm.py
bpm_ai_core/text_classification/__init__.py
bpm_ai_core/text_classification/text_classifier.py
bpm_ai_core/token_classification/__init__.py
bpm_ai_core/token_classification/zero_shot_token_classifier.py
bpm_ai_core/tracing/__init__.py
bpm_ai_core/tracing/decorators.py
bpm_ai_core/tracing/delegate.py
bpm_ai_core/tracing/langfuse.py
bpm_ai_core/tracing/logging.py
bpm_ai_core/tracing/tracer.py
bpm_ai_core/tracing/tracing.py
bpm_ai_core/translation/__init__.py
bpm_ai_core/translation/amazon_translate.py
bpm_ai_core-2.7.1.dist-info/METADATA
bpm_ai_core-2.7.1.dist-info/WHEEL
bpm_ai_core-2.7.1.dist-info/RECORD
