Metadata-Version: 2.3
Name: bpm-ai-core
Version: 2.7.1
Summary: Core AI abstractions and helpers.
License: Apache-2.0
Author: Bennet Krause
Author-email: bennet.krause@holisticon.de
Requires-Python: >=3.11,<4.0
Classifier: License :: OSI Approved :: Apache Software License
Classifier: Programming Language :: Python :: 3
Classifier: Programming Language :: Python :: 3.11
Classifier: Programming Language :: Python :: 3.12
Classifier: Programming Language :: Python :: 3.13
Requires-Dist: aiohttp (>=3.9.3,<4.0.0)
Requires-Dist: diskcache (>=5.6.3,<6.0.0)
Requires-Dist: jinja2 (>=3.1.3,<4.0.0)
Requires-Dist: pdf2image (>=1.17.0,<2.0.0)
Requires-Dist: pillow (>=10.1.0,<11.0.0)
Requires-Dist: psutil (>=6.1.0,<7.0.0)
Requires-Dist: pydantic (==2.9.2)
Requires-Dist: pypdfium2 (>=4.29.0,<5.0.0)
Requires-Dist: requests (>=2.31.0,<3.0.0)
Requires-Dist: tenacity (>=8.2.3,<9.0.0)
Requires-Dist: xmltodict (>=0.13.0,<0.14.0)
Project-URL: Homepage, https://www.holisticon.de/
Project-URL: Repository, https://github.com/holunda-io/bpm-ai
